flake8_fine_pytest/__init__.py
flake8_fine_pytest/ast_helpers.py
flake8_fine_pytest/checker.py
flake8_fine_pytest/common_types.py
flake8_fine_pytest/utils.py
flake8_fine_pytest/watchers/__init__.py
flake8_fine_pytest/watchers/assert_count.py
flake8_fine_pytest/watchers/base.py
flake8_fine_pytest/watchers/modules_structure.py
flake8_fine_pytest/watchers/signature_complexity.py
flake8_fine_pytest/watchers/unique_test_names.py
flake8_fine_pytest/watchers/usefixtures.py
flake8_fine_pytest/watchers/xfail_decorator.py
flake8_fine_pytest/watchers/xfail_until_argument_watcher.py
flake8_fine_pytest-1.0.3.dist-info/LICENSE
flake8_fine_pytest-1.0.3.dist-info/METADATA
flake8_fine_pytest-1.0.3.dist-info/WHEEL
flake8_fine_pytest-1.0.3.dist-info/entry_points.txt
flake8_fine_pytest-1.0.3.dist-info/top_level.txt
flake8_fine_pytest-1.0.3.dist-info/RECORD
